MANIFEST.in
README.rst
setup.cfg
setup.py
django_tms_kk.egg-info/PKG-INFO
django_tms_kk.egg-info/SOURCES.txt
django_tms_kk.egg-info/dependency_links.txt
django_tms_kk.egg-info/requires.txt
django_tms_kk.egg-info/top_level.txt
taskAPI/__init__.py
taskAPI/admin.py
taskAPI/apps.py
taskAPI/models.py
taskAPI/serializers.py
taskAPI/tests.py
taskAPI/urls.py
taskAPI/views.py
taskAPI/migrations/0001_initial.py
taskAPI/migrations/__init__.py